WanmeiZhuyiEshaXiaolv/README.md
WanmeiZhuyiEshaXiaolv/__init__.py
WanmeiZhuyiEshaXiaolv/__main__.py
WanmeiZhuyiEshaXiaolv/file.epub
WanmeiZhuyiEshaXiaolv/index.html
WanmeiZhuyiEshaXiaolv/css/__init__.py
WanmeiZhuyiEshaXiaolv/css/annotations.css
WanmeiZhuyiEshaXiaolv/css/main.css
WanmeiZhuyiEshaXiaolv/css/normalize.css
WanmeiZhuyiEshaXiaolv/css/popup.css
WanmeiZhuyiEshaXiaolv/font/__init__.py
WanmeiZhuyiEshaXiaolv/font/fontello.eot
WanmeiZhuyiEshaXiaolv/font/fontello.svg
WanmeiZhuyiEshaXiaolv/font/fontello.ttf
WanmeiZhuyiEshaXiaolv/font/fontello.woff
WanmeiZhuyiEshaXiaolv/img/__init__.py
WanmeiZhuyiEshaXiaolv/img/annotator-glyph-sprite.png
WanmeiZhuyiEshaXiaolv/img/annotator-icon-sprite.png
WanmeiZhuyiEshaXiaolv/img/apple-touch-icon.png
WanmeiZhuyiEshaXiaolv/img/cancelfullscreen.png
WanmeiZhuyiEshaXiaolv/img/close.png
WanmeiZhuyiEshaXiaolv/img/fullscreen.png
WanmeiZhuyiEshaXiaolv/img/loader.gif
WanmeiZhuyiEshaXiaolv/img/menu-icon.png
WanmeiZhuyiEshaXiaolv/img/save.png
WanmeiZhuyiEshaXiaolv/img/saved.png
WanmeiZhuyiEshaXiaolv/img/settings-s.png
WanmeiZhuyiEshaXiaolv/img/settings.png
WanmeiZhuyiEshaXiaolv/img/star.png
WanmeiZhuyiEshaXiaolv/js/__init__.py
WanmeiZhuyiEshaXiaolv/js/epub.js
WanmeiZhuyiEshaXiaolv/js/epub.min.js
WanmeiZhuyiEshaXiaolv/js/epub.min.map
WanmeiZhuyiEshaXiaolv/js/hooks.min.js
WanmeiZhuyiEshaXiaolv/js/hooks.min.map
WanmeiZhuyiEshaXiaolv/js/reader.js
WanmeiZhuyiEshaXiaolv/js/reader.js.map
WanmeiZhuyiEshaXiaolv/js/reader.min.js
WanmeiZhuyiEshaXiaolv/js/reader.min.map
WanmeiZhuyiEshaXiaolv/js/hooks/__init__.py
WanmeiZhuyiEshaXiaolv/js/hooks/extensions/__init__.py
WanmeiZhuyiEshaXiaolv/js/hooks/extensions/highlight.js
WanmeiZhuyiEshaXiaolv/js/libs/__init__.py
WanmeiZhuyiEshaXiaolv/js/libs/jquery.min.js
WanmeiZhuyiEshaXiaolv/js/libs/localforage.min.js
WanmeiZhuyiEshaXiaolv/js/libs/screenfull.js
WanmeiZhuyiEshaXiaolv/js/libs/screenfull.min.js
WanmeiZhuyiEshaXiaolv/js/libs/zip.min.js
WanmeiZhuyiEshaXiaolv/js/plugins/__init__.py
wanmei_zhuyi_esha_xiaolv-2022.10.15.0.dist-info/METADATA
wanmei_zhuyi_esha_xiaolv-2022.10.15.0.dist-info/WHEEL
wanmei_zhuyi_esha_xiaolv-2022.10.15.0.dist-info/entry_points.txt
wanmei_zhuyi_esha_xiaolv-2022.10.15.0.dist-info/top_level.txt
wanmei_zhuyi_esha_xiaolv-2022.10.15.0.dist-info/RECORD
